nbx/__init__.py
nbx/app.py
nbx/cli.py
nbx/config.py
nbx/gist.py
nbx/link.py
nbx/logger.py
nbx/nbx.py
nbx/note.py
nbx/tui.py
nbx/util.py
nbx/frontend/dist/favicon.ico
nbx/frontend/dist/icon.png
nbx/frontend/dist/index.html
nbx/frontend/dist/assets/index.09b57cf6.css
nbx/frontend/dist/assets/index.742f4719.js
nbx/frontend/dist/assets/index.742f4719.js.map
nbx/frontend/dist/assets/tinykeys.module.d8e12cf8.js
nbx/frontend/dist/assets/tinykeys.module.d8e12cf8.js.map
nbx/ner/__init__.py
nbx/ner/ner.py
nbx/search/__init__.py
nbx/search/faiss.py
nbx/search/mock.py
nbx/search/openai.py
nbx/search/regex.py
nbx/search/search.py
nbx/search/txtai.py
nbx/search/whoosh.py
pynbx-0.0.11.dist-info/METADATA
pynbx-0.0.11.dist-info/WHEEL
pynbx-0.0.11.dist-info/entry_points.txt
pynbx-0.0.11.dist-info/top_level.txt
pynbx-0.0.11.dist-info/RECORD
