Metadata-Version: 2.1
Name: pynbx
Version: 0.0.11
Summary: Next generation of knolwedge management
Home-page: https://github.com/WorkshopHQ/nbx
Author: Tan Li
Author-email: tan@tanli.dev
Project-URL: Bug Tracker, https://github.com/WorkshopHQ/nbx/issues
Project-URL: Changelog, https://github.com/WorkshopHQ/nbx/releases
Classifier: Programming Language :: Python :: 3
Classifier: License :: OSI Approved :: MIT License
Classifier: Operating System :: OS Independent
Requires-Python: >=3.8
Requires-Dist: beautifulsoup4
Requires-Dist: fastapi
Requires-Dist: html2text
Requires-Dist: markdown
Requires-Dist: psutil
Requires-Dist: rich
Requires-Dist: textual
Requires-Dist: typer
Requires-Dist: uvicorn[standard]
Requires-Dist: whoosh
Requires-Dist: pyarrow
Requires-Dist: tantivy ==0.20.1
Requires-Dist: datasets
Requires-Dist: faiss-cpu
Requires-Dist: openai
Requires-Dist: sacremoses
Requires-Dist: sentence-transformers
Requires-Dist: transformers
Requires-Dist: txtai
Requires-Dist: lancedb
Provides-Extra: dev
Requires-Dist: black ; extra == 'dev'
Requires-Dist: Faker ; extra == 'dev'
Requires-Dist: flake8 ; extra == 'dev'
Requires-Dist: isort ; extra == 'dev'
Requires-Dist: memray ; extra == 'dev'
Requires-Dist: pdbpp ; extra == 'dev'
Requires-Dist: pytest ; extra == 'dev'
Requires-Dist: richbench ; extra == 'dev'
